tentakel/__init__.py
tentakel/config.py
tentakel/error.py
tentakel/main.py
tentakel/plugins/__init__.py
tentakel/plugins/rsh.py
tentakel/plugins/ssh.py
tentakel/remote.py
tentakel/shell.py
tentakel/tpg.py
tentakel-4.0.3.dist-info/METADATA
tentakel-4.0.3.dist-info/WHEEL
tentakel-4.0.3.dist-info/entry_points.txt
tentakel-4.0.3.dist-info/RECORD
