Metadata-Version: 2.1
Name: tentakel
Version: 4.0.3
Summary: distributed command execution
Home-page: https://github.com/sfermigier/tentakel
License: BSD
Author: Sebastian Stark, Marlon Berlin
Author-email: cran@users.sourceforge.net, imaginat@users.sourceforge.net
Maintainer: Stefane Fermigier
Maintainer-email: sf@abilian.com
Requires-Python: >=3.9,<4.0
Classifier: License :: Other/Proprietary License
Classifier: Programming Language :: Python :: 3
Classifier: Programming Language :: Python :: 3.9
Classifier: Programming Language :: Python :: 3.10
Classifier: Programming Language :: Python :: 3.11
Classifier: Programming Language :: Python :: 3.12
